{
  "generator-jhipster": {
    "promptValues": {
      "packageName": "com.lxisoft.redalert"
    },
    "jhipsterVersion": "4.13.3",
    "baseName": "RedAlert",
    "packageName": "com.lxisoft.redalert",
    "packageFolder": "com/lxisoft/redalert",
    "serverPort": "8081",
    "authenticationType": "oauth2",
    "cacheProvider": "no",
    "websocket": false,
    "databaseType": "sql",
    "devDatabaseType": "mysql",
    "prodDatabaseType": "mysql",
    "searchEngine": false,
    "messageBroker": false,
    "serviceDiscoveryType": false,
    "buildTool": "maven",
    "enableSocialSignIn": false,
    "enableSwaggerCodegen": false,
    "jwtSecretKey": "9bee7be6bb5759902679b83dd396980775ef17f3",
    "enableTranslation": false,
    "applicationType": "microservice",
    "testFrameworks": [],
    "jhiPrefix": "jhi",
    "clientPackageManager": "yarn",
    "skipClient": true,
    "skipUserManagement": true
  }
}